[
  { "starttime": "7:00pm", "endtime": "9:00pm", "date": "9/8/2025", "location": "Crapo G308" },
  { "starttime": "7:00pm", "endtime": "9:00pm", "date": "9/15/2025", "location": "Crapo G308" },
  { "starttime": "7:00pm", "endtime": "9:00pm", "date": "9/22/2025", "location": "Crapo G308" },
  { "starttime": "7:00pm", "endtime": "9:00pm", "date": "9/29/2025", "location": "Crapo G308" },
  { "starttime": "7:00pm", "endtime": "9:00pm", "date": "10/6/2025", "location": "Crapo G308" },
  { "starttime": "7:00pm", "endtime": "9:00pm", "date": "10/13/2025", "location": "Crapo G308" },
  { "starttime": "7:00pm", "endtime": "9:00pm", "date": "10/20/2025", "location": "Crapo G308" },
  { "starttime": "7:00pm", "endtime": "9:00pm", "date": "10/27/2025", "location": "Crapo G308" },
  { "starttime": "7:00pm", "endtime": "9:00pm", "date": "11/3/2025", "location": "Crapo G308" },
  { "starttime": "7:00pm", "endtime": "9:00pm", "date": "11/10/2025", "location": "Crapo G308" },
  { "starttime": "7:00pm", "endtime": "9:00pm", "date": "12/1/2025", "location": "Crapo G308" },
  { "starttime": "7:00pm", "endtime": "9:00pm", "date": "12/8/2025", "location": "Crapo G308" },
  { "starttime": "7:00pm", "endtime": "9:00pm", "date": "1/5/2026", "location": "Crapo G308" },
  { "starttime": "7:00pm", "endtime": "9:00pm", "date": "1/12/2026", "location": "Crapo G308" },
  { "starttime": "7:00pm", "endtime": "9:00pm", "date": "1/26/2026", "location": "Crapo G308" },
  { "starttime": "7:00pm", "endtime": "9:00pm", "date": "2/2/2026", "location": "Crapo G308" },
  { "starttime": "7:00pm", "endtime": "9:00pm", "date": "2/9/2026", "location": "Crapo G308" },
  { "starttime": "7:00pm", "endtime": "9:00pm", "date": "2/16/2026", "location": "Crapo G308" },
  { "starttime": "7:00pm", "endtime": "9:00pm", "date": "3/9/2026", "location": "Crapo G308" },
  { "starttime": "7:00pm", "endtime": "9:00pm", "date": "3/16/2026", "location": "Crapo G308" },
  { "starttime": "7:00pm", "endtime": "9:00pm", "date": "3/23/2026", "location": "Crapo G308" },
  { "starttime": "7:00pm", "endtime": "9:00pm", "date": "3/30/2026", "location": "Crapo G308" },
  { "starttime": "7:00pm", "endtime": "9:00pm", "date": "4/6/2026", "location": "Crapo G308" },
  { "starttime": "7:00pm", "endtime": "9:00pm", "date": "4/20/2026", "location": "Crapo G308" },
  { "starttime": "7:00pm", "endtime": "9:00pm", "date": "4/27/2026", "location": "Crapo G308" },
  { "starttime": "7:00pm", "endtime": "9:00pm", "date": "5/4/2026", "location": "Crapo G308" },
  { "starttime": "7:00pm", "endtime": "9:00pm", "date": "5/11/2026", "location": "Crapo G308" },
  { "starttime": "7:00pm", "endtime": "9:00pm", "date": "5/18/2026", "location": "Crapo G308" }
]
